odoo/addons/stock_putaway_product_form/README.rst
odoo/addons/stock_putaway_product_form/__init__.py
odoo/addons/stock_putaway_product_form/__manifest__.py
odoo/addons/stock_putaway_product_form/hooks.py
odoo/addons/stock_putaway_product_form/demo/putaway_strategies.xml
odoo/addons/stock_putaway_product_form/i18n/stock_putaway_product_form.pot
odoo/addons/stock_putaway_product_form/models/__init__.py
odoo/addons/stock_putaway_product_form/models/product_product.py
odoo/addons/stock_putaway_product_form/models/product_template.py
odoo/addons/stock_putaway_product_form/models/putaway_strategy.py
odoo/addons/stock_putaway_product_form/readme/CONTRIBUTORS.rst
odoo/addons/stock_putaway_product_form/readme/DESCRIPTION.rst
odoo/addons/stock_putaway_product_form/readme/USAGE.rst
odoo/addons/stock_putaway_product_form/static/description/icon.png
odoo/addons/stock_putaway_product_form/static/description/index.html
odoo/addons/stock_putaway_product_form/tests/__init__.py
odoo/addons/stock_putaway_product_form/tests/test_product_putaway.py
odoo/addons/stock_putaway_product_form/views/product.xml
odoo12_addon_stock_putaway_product_form-12.0.1.0.1.dist-info/METADATA
odoo12_addon_stock_putaway_product_form-12.0.1.0.1.dist-info/WHEEL
odoo12_addon_stock_putaway_product_form-12.0.1.0.1.dist-info/top_level.txt
odoo12_addon_stock_putaway_product_form-12.0.1.0.1.dist-info/RECORD
