Metadata-Version: 2.1
Name: odoo12-addon-stock-putaway-product-form
Version: 12.0.1.0.1
Summary: Edit putaway strategies directly from the product form view
Home-page: https://github.com/OCA/stock-logistics-warehouse
Author: Akretion, Odoo Community Association (OCA)
Author-email: support@odoo-community.org
License: AGPL-3
Platform: UNKNOWN
Classifier: Programming Language :: Python
Classifier: Framework :: Odoo
Classifier: License :: OSI Approved :: GNU Affero General Public License v3
Requires-Python: >=3.5
Requires-Dist: odoo (<12.1dev,>=12.0a)
Requires-Dist: openupgradelib
